CODE_OF_CONDUCT.md
CONTRIBUTING.md
LICENSE
MANIFEST.in
PULL_REQUEST_TEMPLATE.md
README.md
README.rst
requirements.txt
setup.cfg
setup.py
gd_scylla.egg-info/PKG-INFO
gd_scylla.egg-info/SOURCES.txt
gd_scylla.egg-info/dependency_links.txt
gd_scylla.egg-info/entry_points.txt
gd_scylla.egg-info/requires.txt
gd_scylla.egg-info/top_level.txt
scylla/__init__.py
scylla/__main__.py
scylla/_version.py
scylla/cli.py
scylla/config.py
scylla/database.py
scylla/jobs.py
scylla/loggings.py
scylla/proxy_check_services.py
scylla/scheduler.py
scylla/tcpping.py
scylla/validation_policy.py
scylla/validator.py
scylla/worker.py
scylla/providers/__init__.py
scylla/providers/a2u_provider.py
scylla/providers/base_provider.py
scylla/providers/checkerproxy_provider.py
scylla/providers/comp0_provider.py
scylla/providers/cool_proxy_provider.py
scylla/providers/data5u_provider.py
scylla/providers/free_proxy_list_provider.py
scylla/providers/freeproxylist_appspot_provider.py
scylla/providers/github_fate0_provide.py
scylla/providers/hidemyip_provider.py
scylla/providers/hidemyname_provider.py
scylla/providers/http_proxy_provider.py
scylla/providers/ipaddress_provider.py
scylla/providers/kuaidaili_provider.py
scylla/providers/plain_text_provider.py
scylla/providers/proxy11_provider.py
scylla/providers/proxy_list_download_provider.py
scylla/providers/proxy_list_provider.py
scylla/providers/proxy_scraper_provider.py
scylla/providers/proxy_us_provider.py
scylla/providers/proxydaily_provider.py
scylla/providers/proxylisticu_provider.py
scylla/providers/proxylists_provider.py
scylla/providers/proxynova_provider.py
scylla/providers/proxyrack_provider.py
scylla/providers/pubproxy_provider.py
scylla/providers/rmccurdy_provider.py
scylla/providers/rudnkh_provider.py
scylla/providers/seotoolsblog_provider.py
scylla/providers/spys_me_provider.py
scylla/providers/spys_one_provider.py
scylla/providers/sslproxies_provider.py
scylla/providers/the_speedX_provider.py
scylla/providers/xici_provider.py
scylla/proxy/__init__.py
scylla/proxy/server.py
scylla/web/__init__.py
scylla/web/server.py