Metadata-Version: 1.2
Name: gd-scylla
Version: 10.0.0
Summary: Intelligent proxy pool for Humans™
Home-page: https://github.com/imWildCat/scylla
Author: Greendeck
Author-email: wildcat.name@gmail.com
License: UNKNOWN
Keywords: proxy,api,scylla
Platform: UNKNOWN
Classifier: Programming Language :: Python
Classifier: Programming Language :: Python :: 3.6
Classifier: Programming Language :: Python :: Implementation :: CPython
Classifier: Programming Language :: Python :: Implementation :: PyPy
Classifier: License :: OSI Approved :: Apache Software License
Requires-Python: >=3.6.0
